alfred_osint/.github/FUNDING.yml
alfred_osint/.github/ISSUE_TEMPLATE/bug_report.md
alfred_osint/.github/ISSUE_TEMPLATE/feature_request.md
alfred_osint/CODE_OF_CONDUCT.md
alfred_osint/CONTRIBUTING.md
alfred_osint/LICENSE
alfred_osint/README.md
alfred_osint/SECURITY.md
alfred_osint/brib.py
alfred_osint/captured/captured.alfred
alfred_osint/captured/working.txt
alfred_osint/config/config.ini
alfred_osint/config/tips.txt
alfred_osint/config/udfl
alfred_osint/config/version.cfg
alfred_osint/kali.txt
alfred_osint/modules/__init__.py
alfred_osint/modules/configcheck.py
alfred_osint/modules/crypt.py
alfred_osint/modules/modules.py
alfred_osint/modules/printmodules.py
alfred_osint/modules/recive.py
alfred_osint/modules/scanmodules.py
alfred_osint/modules/sender.py
alfred_osint/modules/siteListGen.py
alfred_osint/modules/webscrape.py
alfred_osint/newwrkingsotes.txt
alfred_osint/proxys/http.txt
alfred_osint/proxys/proxylist.txt
alfred_osint/proxys/socks4.txt
alfred_osint/proxys/socks5.txt
alfred_osint/requirements.txt
alfred_osint/sites/Megasites.json
alfred_osint/sites/SmallSItes.txt
alfred_osint/sites/fsites.json
alfred_osint/sites/siteList.json
alfred_osint/sites/sites.json
alfred_osint/update.py
alfred_osint-2.2.dist-info/LICENSE
alfred_osint-2.2.dist-info/METADATA
alfred_osint-2.2.dist-info/WHEEL
alfred_osint-2.2.dist-info/RECORD
