Metadata-Version: 2.1
Name: alfred-osint
Version: 2.2
Summary: Alfred is a advanced OSINT information gathering tool
License: MIT
Author: EliteGreyIT67
Author-email: jpinky67@gmail.com
Requires-Python: >=3.11,<4.0
Classifier: License :: OSI Approved :: MIT License
Classifier: Programming Language :: Python :: 3
Classifier: Programming Language :: Python :: 3.11
Classifier: Programming Language :: Python :: 3.12
Requires-Dist: alive-progress (>=3.1.5,<4.0.0)
Requires-Dist: bs4 (>=0.0.1,<0.0.2)
Requires-Dist: colorama (>=0.4.6,<0.5.0)
Requires-Dist: cryptography (>=41.0.7,<42.0.0)
Requires-Dist: requests (>=2.31.0,<3.0.0)
Requires-Dist: rich (>=13.7.0,<14.0.0)
Requires-Dist: selenium (>=4.15.2,<5.0.0)
Requires-Dist: torrequest (>=0.1.0,<0.2.0)
Requires-Dist: tqdm (>=4.66.1,<5.0.0)
Requires-Dist: wget (>=3.2,<4.0)
